ALU.v
`timescale 1ns/1ps
module ALU (

  input [31:0]in1,
  input [31:0]in2,
  input [3:0] aluControl,
  input [4:0] shamt,
  output reg zero,
  output reg [31:0] out
  );
  
  always @( * ) begin
    if (aluControl==4'b0000) begin
      out=in1+in2;
    end
    else if (aluControl==4'b0001) begin
      out=in1-in2;
    end
    else if (aluControl==4'b0010) begin
      out=~in1;
    end
    else if (aluControl==4'b0011) begin
      out=in1<<shamt;
    end
    else if (aluControl==4'b0100) begin
      out=in1>>shamt;
    end
    else if (aluControl==4'b0101) begin
      out=in1&in2;
    end
    else if (aluControl==4'b0110) begin
      out=in1|in2;
    end
    else if (aluControl==4'b0111) begin
      if (in1<in2) begin
        out=1;
      end
      else begin
        out=0;
      end
    end




  end

always @(*) begin
  if (out==0) begin
    zero=1;
  end
  else begin
    zero=0;
  end
end
  
endmodule

ALUTest.v
`timescale  1ns / 1ps
`include "ALU.v"

module ALUTest;       


// ALU Inputs
reg   [31:0]  in1                          = 0 ;
reg   [31:0]  in2                          = 0 ;
reg   [3:0]  aluControl                    = 0 ;
reg   [4:0]  shamt                         = 0 ;

// ALU Outputs
wire  zero                                 ;
wire  [31:0]  out                          ;


ALU  u_ALU (
    .in1                     ( in1         [31:0] ),
    .in2                     ( in2         [31:0] ),
    .aluControl              ( aluControl  [3:0]  ),
    .shamt                   ( shamt       [4:0]  ),

    .zero                    ( zero               ),
    .out                     ( out         [31:0] )
);

initial
begin
    $dumpfile("ALU.vcd");
    $dumpvars(0,ALUTest);
end


initial
begin
    in1=4;
    in2=2;
    shamt=2;
    aluControl=4'b0000;
    #200
    aluControl=4'b0001;
    #200
    aluControl=4'b0010;
    #200
    aluControl=4'b0011;
    #200
    aluControl=4'b0100;
    #200
    aluControl=4'b0101;
    #200
    aluControl=4'b0110;
    #200
    aluControl=4'b0111;
    #200
    in1=2;
    in2=2;
    aluControl=4'b0001;
    #200
    $finish;
end

endmodule

ALU.vcd
$date
	Wed Oct 30 09:14:23 2024
$end
$version
	Icarus Verilog
$end
$timescale
	1ps
$end
$scope module ALUTest $end
$var wire 1 ! zero $end
$var wire 32 " out [31:0] $end
$var reg 4 # aluControl [3:0] $end
$var reg 32 $ in1 [31:0] $end
$var reg 32 % in2 [31:0] $end
$var reg 5 & shamt [4:0] $end
$scope module u_ALU $end
$var wire 4 ' aluControl [3:0] $end
$var wire 32 ( in1 [31:0] $end
$var wire 32 ) in2 [31:0] $end
$var wire 5 * shamt [4:0] $end
$var reg 32 + out [31:0] $end
$var reg 1 ! zero $end
$upscope $end
$upscope $end
$enddefinitions $end
$comment Show the parameter values. $end
$dumpall
$end
#0
$dumpvars
b110 +
b10 *
b10 )
b100 (
b0 '
b10 &
b10 %
b100 $
b0 #
b110 "
0!
$end
#200000
b10 "
b10 +
b1 #
b1 '
#400000
b11111111111111111111111111111011 "
b11111111111111111111111111111011 +
b10 #
b10 '
#600000
b10000 "
b10000 +
b11 #
b11 '
#800000
b1 "
b1 +
b100 #
b100 '
#1000000
1!
b0 "
b0 +
b101 #
b101 '
#1200000
0!
b110 "
b110 +
b110 #
b110 '
#1400000
1!
b0 "
b0 +
b111 #
b111 '
#1600000
b1 #
b1 '
b10 $
b10 (
