ALUControl.v
`timescale 1ns/1ps
module ALUControl (
  input [2:0]ALUOp,
  input [5:0] in1,
  output reg [3:0] ALUcnt
  );
  
  always @(*) begin
    if (ALUOp==3'b000) begin
      if (in1==6'b000000) begin
        ALUcnt=4'b0000;
      end
      else if (in1==6'b000001) begin
        ALUcnt=4'b0001;
      end
      else if (in1==6'b000010) begin
        ALUcnt=4'b0101;
      end
      else if (in1==6'b000011) begin
        ALUcnt=4'b0110;
      end
      else if (in1==6'b000100) begin
        ALUcnt=4'b0111;
      end
      else if (in1==6'b000101) begin
        ALUcnt=4'b0011;
      end
      else if (in1==6'b000110) begin
          ALUcnt=4'b0100;
        
      end
      else if (in1==6'b000111) begin
       ALUcnt=4'b0010;
      end
    end
    else if (ALUOp==3'b001) begin
      ALUcnt=4'b0001;
    end
    else if (ALUOp==3'b010) begin
    ALUcnt=4'b0111;
    end
    else if (ALUOp==3'b011) begin
    ALUcnt=4'b0000;
    end
    
  end
  
endmodule

ALUControlTest.v
`timescale  1ns / 1ps
`include "ALUControl.v"


module ALUControlTest;



// aluControl Inputs
reg   [5:0]  in1                           = 0 ;
reg   [2:0]  ALUOp                         = 0 ;

// aluControl Outputs
wire  [3:0]  ALUcnt                        ;



ALUControl  u_ALUControl (
    .in1                     ( in1     [5:0] ),
    .ALUOp                   ( ALUOp   [2:0] ),

    .ALUcnt                  ( ALUcnt  [3:0] )
);

initial
begin
    $dumpfile("ALUControl.vcd");
    $dumpvars(0,ALUControlTest);
end

initial
begin

    ALUOp = 3'b000;
    in1 = 6'b000000;
    #200
    in1 = 6'b000001;
    #200
    in1 = 6'b000010;
    #200
    in1 = 6'b000011;
    #200
    in1 = 6'b000100;
    #200
    in1 = 6'b000101;
    #200
    in1 = 6'b000110;
    #200
    in1 = 6'b000111;
    #200
    ALUOp = 3'b001;
    #200
    ALUOp = 3'b010;
    #200
    ALUOp = 3'b011;
    #200

    $finish;
end

endmodule

ALUControl.vcd
$date
	Wed Oct 30 09:53:02 2024
$end
$version
	Icarus Verilog
$end
$timescale
	1ps
$end
$scope module ALUControlTest $end
$var wire 4 ! ALUcnt [3:0] $end
$var reg 3 " ALUOp [2:0] $end
$var reg 6 # in1 [5:0] $end
$scope module u_ALUControl $end
$var wire 3 $ ALUOp [2:0] $end
$var wire 6 % in1 [5:0] $end
$var reg 4 & ALUcnt [3:0] $end
$upscope $end
$upscope $end
$enddefinitions $end
$comment Show the parameter values. $end
$dumpall
$end
#0
$dumpvars
b0 &
b0 %
b0 $
b0 #
b0 "
b0 !
$end
#200000
b1 !
b1 &
b1 #
b1 %
#400000
b101 !
b101 &
b10 #
b10 %
#600000
b110 !
b110 &
b11 #
b11 %
#800000
b111 !
b111 &
b100 #
b100 %
#1000000
b11 !
b11 &
b101 #
b101 %
#1200000
b100 !
b100 &
b110 #
b110 %
#1400000
b10 !
b10 &
b111 #
b111 %
#1600000
b1 !
b1 &
b1 "
b1 $
#1800000
b111 !
b111 &
b10 "
b10 $
#2000000
b0 !
b0 &
b11 "
b11 $
