DataMemory.v
`timescale 1ns/1ps

module DataMemory (
    input clk,
    input writeSig,
    input [31:0] address,
    input [31:0] inData,
    output reg [127:0] out
);

    reg [31:0] addressTemp;
    reg [7:0] memory [1024:0];
    reg [2:0] clock=0;

    always @(negedge clk) begin
        if (writeSig) begin
            memory[address]=inData[31:24];
            memory[address+1]=inData[23:16];
            memory[address+2]=inData[15:8];
            memory[address+3]=inData[7:0];
        end
    end

    always @(posedge clk) begin
        addressTemp=address;
        clock=clock+1;
        if (clock==5) begin
            addressTemp[3:0]=0;
            out={memory[addressTemp],memory[addressTemp+1],memory[addressTemp+2],memory[addressTemp+3],memory[addressTemp+4],memory[addressTemp+5],memory[addressTemp+6],memory[addressTemp+7],memory[addressTemp+8],memory[addressTemp+9],memory[addressTemp+10],memory[addressTemp+11],memory[addressTemp+12],memory[addressTemp+13],memory[addressTemp+14],memory[addressTemp+15]};
        end
    end

    always @(address) begin
        clock=0;
    end

endmodule

DataMemoryTest.v
`timescale  1ns / 1ps
`include "DataMemory.v"

module DataMemoryTest;   


// DataMemory Inputs
reg   clk                                  = 0 ;
reg   writeSig                             = 0 ;
reg   [31:0]  address                      = 0 ;
reg   [31:0]  inData                       = 0 ;

// DataMemory Outputs
wire  [127:0]  out                         ;


DataMemory  u_DataMemory (
    .clk                     ( clk               ),
    .writeSig                ( writeSig          ),
    .address                 ( address   [31:0]  ),
    .inData                  ( inData    [31:0]  ),

    .out                     ( out       [127:0] )
);

initial
begin
    $dumpfile("DM.vcd");
    $dumpvars(0,DataMemoryTest);
end

initial
begin

    address=0;
    writeSig=1;
    inData=7;
    #200
    address=20;
    writeSig=1;
    inData=15;
    #200
    writeSig=0;
    address=5;
    #100
    address=17;
    #800

    $finish;
end
always #50 clk=~clk;

endmodule

DM.vcd
$date
	Wed Dec  4 09:34:19 2024
$end
$version
	Icarus Verilog
$end
$timescale
	1ps
$end
$scope module DataMemoryTest $end
$var wire 128 ! out [127:0] $end
$var reg 32 " address [31:0] $end
$var reg 1 # clk $end
$var reg 32 $ inData [31:0] $end
$var reg 1 % writeSig $end
$scope module u_DataMemory $end
$var wire 32 & address [31:0] $end
$var wire 1 # clk $end
$var wire 32 ' inData [31:0] $end
$var wire 1 % writeSig $end
$var reg 32 ( addressTemp [31:0] $end
$var reg 3 ) clock [2:0] $end
$var reg 128 * out [127:0] $end
$upscope $end
$upscope $end
$enddefinitions $end
$comment Show the parameter values. $end
$dumpall
$end
#0
$dumpvars
bx *
b0 )
bx (
b111 '
b0 &
1%
b111 $
0#
b0 "
bx !
$end
#50000
b1 )
b0 (
1#
#100000
0#
#150000
b10 )
1#
#200000
b0 )
0#
b1111 $
b1111 '
b10100 "
b10100 &
#250000
b1 )
b10100 (
1#
#300000
0#
#350000
b10 )
1#
#400000
b0 )
0#
b101 "
b101 &
0%
#450000
b1 )
b101 (
1#
#500000
b0 )
0#
b10001 "
b10001 &
#550000
b1 )
b10001 (
1#
#600000
0#
#650000
b10 )
1#
#700000
0#
#750000
b11 )
1#
#800000
0#
#850000
b100 )
1#
#900000
0#
#950000
bx00000000000000000000000000001111xxxxxxxxxxxxxxxxxxxxxxxxxxxxxxxxxxxxxxxxxxxxxxxxxxxxxxxxxxxxxxxx !
bx00000000000000000000000000001111xxxxxxxxxxxxxxxxxxxxxxxxxxxxxxxxxxxxxxxxxxxxxxxxxxxxxxxxxxxxxxxx *
b10000 (
b101 )
1#
#1000000
0#
#1050000
b110 )
b10001 (
1#
#1100000
0#
#1150000
b111 )
1#
#1200000
0#
#1250000
b0 )
1#
